ghsu/__init__.py
ghsu/ghsu.py
ghsu-0.1.0.dist-info/LICENSE
ghsu-0.1.0.dist-info/METADATA
ghsu-0.1.0.dist-info/WHEEL
ghsu-0.1.0.dist-info/entry_points.txt
ghsu-0.1.0.dist-info/top_level.txt
ghsu-0.1.0.dist-info/RECORD
